tiwave/__init__.py
tiwave/constants.py
tiwave/utils.py
tiwave/waveforms/IMRPhenomD.py
tiwave/waveforms/IMRPhenomXAS.py
tiwave/waveforms/IMRPhenomXHM.py
tiwave/waveforms/IMRPhenomXPHM.py
tiwave/waveforms/__init__.py
tiwave/waveforms/base_waveform.py
tiwave/waveforms/common.py
tiwave/waveforms/data/QNMData_a.txt
tiwave/waveforms/data/QNMData_fdamp.txt
tiwave/waveforms/data/QNMData_fring.txt
tiwave-0.0.0.dist-info/licenses/LICENSE
tiwave-0.0.0.dist-info/METADATA
tiwave-0.0.0.dist-info/WHEEL
tiwave-0.0.0.dist-info/top_level.txt
tiwave-0.0.0.dist-info/RECORD
