Metadata-Version: 2.4
Name: tiwave
Version: 0.0.0
Summary: GW waveforms with taichi-lang.
Author-email: Rui Niu <nrui@mail.ustc.edu.cn>
License-Expression: GPL-3.0-or-later
Project-URL: Documentation, https://github.com/niuiniuin/tiwave
Project-URL: Repository, https://github.com/niuiniuin/tiwave
Keywords: gravitational-wave,taichi-lang,waveform
Classifier: Development Status :: 2 - Pre-Alpha
Classifier: Intended Audience :: Science/Research
Classifier: Programming Language :: Python :: 3
Classifier: Topic :: Scientific/Engineering :: Astronomy
Requires-Python: >=3.10
License-File: LICENSE
Requires-Dist: taichi!=1.7.1
Requires-Dist: numpy
Provides-Extra: dev
Requires-Dist: scipy; extra == "dev"
Requires-Dist: matplotlib; extra == "dev"
Requires-Dist: bilby; extra == "dev"
Requires-Dist: lalsuite; extra == "dev"
Requires-Dist: pytest; extra == "dev"
Requires-Dist: pytest-cov; extra == "dev"
Requires-Dist: black; extra == "dev"
Requires-Dist: mypy; extra == "dev"
Requires-Dist: sphinx; extra == "dev"
Dynamic: license-file
